bee_config/__init__.py
bee_config/_config.py
bee_config/manager.py
bee_config/source.py
py_bee_config-0.1.0.dist-info/LICENSE.rst
py_bee_config-0.1.0.dist-info/METADATA
py_bee_config-0.1.0.dist-info/WHEEL
py_bee_config-0.1.0.dist-info/top_level.txt
py_bee_config-0.1.0.dist-info/RECORD
