Metadata-Version: 2.1
Name: py-bee-config
Version: 0.1.0
Summary: Bee is an all-in-one python framework for simplifying micro service program development.
Home-page: https://github.com/py-bee/bee-config
Author: wenchao.hao
Author-email: awenhaowenchao@hotmail.com
License: MIT
Platform: UNKNOWN
Classifier: License :: OSI Approved :: MIT License
Classifier: Programming Language :: Python
Classifier: Programming Language :: Python :: 3
Classifier: Programming Language :: Python :: 3.6
Classifier: Programming Language :: Python :: Implementation :: CPython
Classifier: Programming Language :: Python :: Implementation :: PyPy
Requires-Python: >=3.6.0
Requires-Dist: pyyaml (>=5.4.1)
